GdbDiaoshiJiaochengCYuyanBianchengWangFix1/README.md
GdbDiaoshiJiaochengCYuyanBianchengWangFix1/__init__.py
GdbDiaoshiJiaochengCYuyanBianchengWangFix1/__main__.py
GdbDiaoshiJiaochengCYuyanBianchengWangFix1/file.epub
GdbDiaoshiJiaochengCYuyanBianchengWangFix1/index.html
GdbDiaoshiJiaochengCYuyanBianchengWangFix1/css/__init__.py
GdbDiaoshiJiaochengCYuyanBianchengWangFix1/css/annotations.css
GdbDiaoshiJiaochengCYuyanBianchengWangFix1/css/main.css
GdbDiaoshiJiaochengCYuyanBianchengWangFix1/css/normalize.css
GdbDiaoshiJiaochengCYuyanBianchengWangFix1/css/popup.css
GdbDiaoshiJiaochengCYuyanBianchengWangFix1/font/__init__.py
GdbDiaoshiJiaochengCYuyanBianchengWangFix1/font/fontello.eot
GdbDiaoshiJiaochengCYuyanBianchengWangFix1/font/fontello.svg
GdbDiaoshiJiaochengCYuyanBianchengWangFix1/font/fontello.ttf
GdbDiaoshiJiaochengCYuyanBianchengWangFix1/font/fontello.woff
GdbDiaoshiJiaochengCYuyanBianchengWangFix1/img/__init__.py
GdbDiaoshiJiaochengCYuyanBianchengWangFix1/img/annotator-glyph-sprite.png
GdbDiaoshiJiaochengCYuyanBianchengWangFix1/img/annotator-icon-sprite.png
GdbDiaoshiJiaochengCYuyanBianchengWangFix1/img/apple-touch-icon.png
GdbDiaoshiJiaochengCYuyanBianchengWangFix1/img/cancelfullscreen.png
GdbDiaoshiJiaochengCYuyanBianchengWangFix1/img/close.png
GdbDiaoshiJiaochengCYuyanBianchengWangFix1/img/fullscreen.png
GdbDiaoshiJiaochengCYuyanBianchengWangFix1/img/loader.gif
GdbDiaoshiJiaochengCYuyanBianchengWangFix1/img/menu-icon.png
GdbDiaoshiJiaochengCYuyanBianchengWangFix1/img/save.png
GdbDiaoshiJiaochengCYuyanBianchengWangFix1/img/saved.png
GdbDiaoshiJiaochengCYuyanBianchengWangFix1/img/settings-s.png
GdbDiaoshiJiaochengCYuyanBianchengWangFix1/img/settings.png
GdbDiaoshiJiaochengCYuyanBianchengWangFix1/img/star.png
GdbDiaoshiJiaochengCYuyanBianchengWangFix1/js/__init__.py
GdbDiaoshiJiaochengCYuyanBianchengWangFix1/js/epub.js
GdbDiaoshiJiaochengCYuyanBianchengWangFix1/js/epub.min.js
GdbDiaoshiJiaochengCYuyanBianchengWangFix1/js/epub.min.map
gdb_diaoshi_jiaocheng_c_yuyan_biancheng_wang_fix1-2025.3.24.1.dist-info/METADATA
gdb_diaoshi_jiaocheng_c_yuyan_biancheng_wang_fix1-2025.3.24.1.dist-info/WHEEL
gdb_diaoshi_jiaocheng_c_yuyan_biancheng_wang_fix1-2025.3.24.1.dist-info/entry_points.txt
gdb_diaoshi_jiaocheng_c_yuyan_biancheng_wang_fix1-2025.3.24.1.dist-info/top_level.txt
gdb_diaoshi_jiaocheng_c_yuyan_biancheng_wang_fix1-2025.3.24.1.dist-info/RECORD
